odoo8_addon_l10n_fr_chorus_sale-8.0.1.0.0.99.dev7-py2.7-nspkg.pth
odoo8_addon_l10n_fr_chorus_sale-8.0.1.0.0.99.dev7.dist-info/METADATA
odoo8_addon_l10n_fr_chorus_sale-8.0.1.0.0.99.dev7.dist-info/RECORD
odoo8_addon_l10n_fr_chorus_sale-8.0.1.0.0.99.dev7.dist-info/WHEEL
odoo8_addon_l10n_fr_chorus_sale-8.0.1.0.0.99.dev7.dist-info/namespace_packages.txt
odoo8_addon_l10n_fr_chorus_sale-8.0.1.0.0.99.dev7.dist-info/top_level.txt
odoo_addons/l10n_fr_chorus_sale/README.rst
odoo_addons/l10n_fr_chorus_sale/__init__.py
odoo_addons/l10n_fr_chorus_sale/__openerp__.py
odoo_addons/l10n_fr_chorus_sale/i18n/l10n_fr_chorus_sale.pot
odoo_addons/l10n_fr_chorus_sale/models/__init__.py
odoo_addons/l10n_fr_chorus_sale/models/public_market.py
odoo_addons/l10n_fr_chorus_sale/models/sale_order.py
odoo_addons/l10n_fr_chorus_sale/static/description/icon.png
odoo_addons/l10n_fr_chorus_sale/views/public_market.xml
odoo_addons/l10n_fr_chorus_sale/views/sale_order.xml
odoo_addons/l10n_fr_chorus_sale/wizard/__init__.py
odoo_addons/l10n_fr_chorus_sale/wizard/sale_line_invoice.py
odoo_addons/l10n_fr_chorus_sale/wizard/sale_make_invoice_advance.py
